README.md
setup.cfg
setup.py
bin/airport-status
bin/appinfo
bin/battery
bin/dialupcontrol
bin/diskimages
bin/getent
bin/ios-backups
bin/location
bin/vpncontrol
bin/vpnssh
darwinist/__init__.py
darwinist/afpshare.py
darwinist/airport.py
darwinist/application.py
darwinist/battery.py
darwinist/corestorage.py
darwinist/diskimage.py
darwinist/diskutil.py
darwinist/interfaces.py
darwinist/ioreg.py
darwinist/location.py
darwinist/networkprofile.py
darwinist/networksetup.py
darwinist/notification.py
darwinist/sdef.py
darwinist/systemevents.py
darwinist/timemachine.py
darwinist/vlan.py
darwinist.egg-info/PKG-INFO
darwinist.egg-info/SOURCES.txt
darwinist.egg-info/dependency_links.txt
darwinist.egg-info/requires.txt
darwinist.egg-info/top_level.txt
darwinist/ios/__init__.py
darwinist/ios/backup.py