Metadata-Version: 1.0
Name: darwinist
Version: 4.8.4
Summary: Sysadmin utility modules and scripts for OS/X
Home-page: https://github.com/hile/darwinist
Author: Ilkka Tuohela
Author-email: hile@iki.fi
License: PSF
Keywords: System Management Utility OS/X Darwin Scripts
Platform: UNKNOWN
